lektor_rst.py
lektor_rst-0.3.0.dist-info/METADATA
lektor_rst-0.3.0.dist-info/WHEEL
lektor_rst-0.3.0.dist-info/entry_points.txt
lektor_rst-0.3.0.dist-info/top_level.txt
lektor_rst-0.3.0.dist-info/RECORD
